ntsc/__init__.py
ntsc/ntsc.py
ntsc/docs/pyntsc_api.doc
ntsc/examples/Case_Config_Start/Create_Start_Multiple_Case.py
ntsc/examples/Case_Config_Start/Import_Case_Config.py
ntsc/examples/Case_Config_Start/Import_Case_From_Zip.py
ntsc/examples/Case_Config_Start/Modify_Case_Default_Parameter.py
ntsc/examples/Case_Config_Start/Start_Existed_Case.py
ntsc/examples/Case_Config_Start/export_case_config.py
ntsc/examples/DDoS_Test/DDoS_IP_Fragment_Flood.py
ntsc/examples/DDoS_Test/DDoS_IP_Fragment_Flood_2509.py
ntsc/examples/Firewall_Gateway_Test/HTTP_CC_ConcurrentConnection.py
ntsc/examples/Firewall_Gateway_Test/HTTP_CC_ConcurrentConnection_2509.py
ntsc/examples/Firewall_Gateway_Test/HTTP_CPS_HelloWorld.py
ntsc/examples/Firewall_Gateway_Test/HTTP_CPS_Overload_ConnectionPerSecond.py
ntsc/examples/Firewall_Gateway_Test/HTTP_CPS_Overload_ConnectionPerSecond_2509.py
ntsc/examples/Firewall_Gateway_Test/HTTP_CPS_Simuser_ConnectionPerSecond.py
ntsc/examples/Firewall_Gateway_Test/HTTP_CPS_Simuser_ConnectionPerSecond_2509.py
ntsc/examples/History_Download/Download_History_Tester_Log.py
ntsc/examples/History_Download/Download_Histroy_Pcap.py
ntsc/examples/RFC2544_Test/RFC2544_Throughput.py
ntsc/examples/RFC2544_Test/RFC2544_Throughput_2509.py
ntsc/examples/Web_Service_Test/HTTP_CPS_ConnectionPerSecond.py
ntsc/examples/Web_Service_Test/HTTP_CPS_ConnectionPerSecond_1.py
pyntsc-25.6.35.5341.dist-info/AUTHORS
pyntsc-25.6.35.5341.dist-info/LICENSE
pyntsc-25.6.35.5341.dist-info/METADATA
pyntsc-25.6.35.5341.dist-info/WHEEL
pyntsc-25.6.35.5341.dist-info/top_level.txt
pyntsc-25.6.35.5341.dist-info/RECORD
