Metadata-Version: 2.1
Name: pyntsc
Version: 25.6.35.5341
Summary: Python Object-Oriented Library to Automate Netitest Network Testing Instruments
Home-page: UNKNOWN
Author: Beijing Netitest Technology Co., Ltd.
Author-email: hfli@netitest.com
License: UNKNOWN
Keywords: netitest,supernova,darkbird,jmeter,ddos,ntsc,pyntsc,keysight,ixia,ixnetwork,ixload,spirent,testcenter,stc,avalanche,trex,xena,l2l3,l4l7,l27,tg,traffic generator,test automation,automation api
Platform: UNKNOWN
Classifier: Programming Language :: Python :: 3
Classifier: Operating System :: OS Independent
Requires-Python: >=3.6
License-File: LICENSE
License-File: AUTHORS
Requires-Dist: ipaddress
Requires-Dist: openpyxl
Requires-Dist: pandas
Requires-Dist: requests
Requires-Dist: wexpect
